Metadata-Version: 1.0
Name: SICA
Version: 2.1.3
Summary: An feature extraction algorithm
Home-page: https://github.com/LiangjunFeng/SICA
Author: LiangjunFeng
Author-email: zhumavip@163.com
License: MIT Licence
Keywords: pip,SICA,featureextraction
Platform: any
